{
    "settings": {
        "categories": [
            {
                "id": "campaign",
                "name": "キャンペーン案件"
            },
            {
                "id": "renewal",
                "name": "サイトリニューアル"
            },
            {
                "id": "operation",
                "name": "定常運用・保守"
            },
            {
                "id": "analysis",
                "name": "分析・レポート"
            },
            {
                "id": "admin",
                "name": "社内業務"
            }
        ],
        "statuses": [
            {
                "id": "not_started",
                "name": "未着手",
                "color": "#999999"
            },
            {
                "id": "in_progress",
                "name": "進行中",
                "color": "#007AFF"
            },
            {
                "id": "internal_check",
                "name": "社内検証中",
                "color": "#FF9500"
            },
            {
                "id": "client_wait",
                "name": "先方確認待ち",
                "color": "#34C759"
            },
            {
                "id": "requires_action",
                "name": "要対応",
                "color": "#D44C47"
            }
        ]
    },
    "tasks": [
        {
            "id": "t_1001",
            "name": "【チェック】本日公開：お知らせ記事の最終検品",
            "status": "requires_action",
            "category": "operation",
            "deadline": "2025/12/26 11:30",
            "memo": "本日公開分。\n誤字脱字、リンク切れ、スマホでの改行位置、Alt属性の設定まで細かく見る。\n\n確認後、沖縄チームへ公開指示を出す。",
            "isArchived": false,
            "isDeleted": false,
            "createdAt": "2025-12-26T09:00:00.000Z",
            "updatedAt": "2025-12-26T09:30:00.000Z",
            "archivedAt": "",
            "subtasks": []
        },
        {
            "id": "t_1002",
            "name": "春の新商品キャンペーンサイト制作進行",
            "status": "internal_check",
            "category": "campaign",
            "deadline": "2025/12/28",
            "memo": "10:00〜 制作進行MTG。\nデザイナー・エンジニアと進捗確認。\n\n懸念点：\nSP（スマホ）でのアニメーション動作が重い可能性あり。実機検証を徹底する。",
            "isArchived": false,
            "isDeleted": false,
            "createdAt": "2025-12-25T10:00:00.000Z",
            "updatedAt": "2025-12-26T10:00:00.000Z",
            "archivedAt": "",
            "subtasks": [
                {
                    "id": "st_1002_1",
                    "name": "デザイン修正チェック（SP版）",
                    "status": "internal_check",
                    "isArchived": false,
                    "deadline": "2025/12/26",
                    "memo": ""
                },
                {
                    "id": "st_1002_2",
                    "name": "実機検証（iOS/Android）",
                    "status": "not_started",
                    "isArchived": false,
                    "deadline": "2025/12/27",
                    "memo": "iPhone SEでの表示崩れがないか重点確認"
                }
            ]
        },
        {
            "id": "t_1003",
            "name": "月次アクセス解析レポート作成（11月度）",
            "status": "in_progress",
            "category": "analysis",
            "deadline": "2025/12/26 14:00",
            "memo": "14:00〜 クライアント定例会で報告。\n\nトピックス：\n・先月の特集ページはPV好調だが、滞在時間が短い。\n・改善提案：ファーストビューに動画を配置するABテストの実施を提案する。\n・Looker Studioのデータ更新確認済み。",
            "isArchived": false,
            "isDeleted": false,
            "createdAt": "2025-12-24T15:00:00.000Z",
            "updatedAt": "2025-12-26T13:00:00.000Z",
            "archivedAt": "",
            "subtasks": []
        },
        {
            "id": "t_1004",
            "name": "更新マニュアル改訂（商品スペック表示ルール変更）",
            "status": "not_started",
            "category": "operation",
            "deadline": "2026/01/10",
            "memo": "クライアント要望：来月からスペック表の表示ルール変更。\n沖縄のオペレーターが迷わないよう、図解入りでマニュアル（PPT）を修正する。\n\n※ここが曖昧だと運用ミスに繋がるため丁寧に。",
            "isArchived": false,
            "isDeleted": false,
            "createdAt": "2025-12-26T16:00:00.000Z",
            "updatedAt": "2025-12-26T16:00:00.000Z",
            "archivedAt": "",
            "subtasks": [
                {
                    "id": "st_1004_1",
                    "name": "新ルールの仕様確認",
                    "status": "done",
                    "isArchived": true,
                    "deadline": "2025/12/25",
                    "memo": ""
                },
                {
                    "id": "st_1004_2",
                    "name": "マニュアル赤入れ・図解作成",
                    "status": "not_started",
                    "isArchived": false,
                    "deadline": "2026/01/08",
                    "memo": ""
                }
            ]
        },
        {
            "id": "t_1005",
            "name": "次四半期・改修案件の見積もり作成",
            "status": "not_started",
            "category": "renewal",
            "deadline": "2025/12/26 18:00",
            "memo": "来期の機能追加改修について。\nリスクを見越してバッファを積んでおくこと。\n\n構成要素：\n・ディレクション工数\n・デザイン工数\n・実装工数（バックエンド連携含む）",
            "isArchived": false,
            "isDeleted": false,
            "createdAt": "2025-12-26T17:00:00.000Z",
            "updatedAt": "2025-12-26T17:00:00.000Z",
            "archivedAt": "",
            "subtasks": []
        },
        {
            "id": "t_1006",
            "name": "沖縄チームからの夜間更新報告チェック",
            "status": "done",
            "category": "operation",
            "deadline": "2025/12/26 09:30",
            "memo": "夜間に依頼していたバナー差し替え作業の完了報告を確認。\n本番環境での表示確認よし。",
            "isArchived": true,
            "isDeleted": false,
            "createdAt": "2025-12-25T18:00:00.000Z",
            "updatedAt": "2025-12-26T09:35:00.000Z",
            "archivedAt": "2025-12-26T09:35:00.000Z",
            "subtasks": []
        },
        {
            "id": "t_1007",
            "name": "CMS構造見直し提案資料作成",
            "status": "not_started",
            "category": "renewal",
            "deadline": "2026/01/15",
            "memo": "「継続的に運用できる設計」を提案する。\n現在の更新フローの問題点を洗い出し、汎用パーツ化による効率化を訴求。",
            "isArchived": false,
            "isDeleted": false,
            "createdAt": "2025-12-20T10:00:00.000Z",
            "updatedAt": "2025-12-20T10:00:00.000Z",
            "archivedAt": "",
            "subtasks": []
        }
    ],
    "globalMemo": "【今月の注力事項】\n・春キャンペーンの無事ローンチ\n・運用マニュアルの刷新（ポカミス撲滅）\n・来期予算獲得のための提案活動\n\n【備忘録】\n・クライアントAさん：月曜午前は会議のため連絡つきにくい\n・AEMのキャッシュクリア手順： https://wiki.example.com/aem/cache-clear"
}